inmanta_plugins/php/__init__.py
inmanta_plugins/php/setup.cfg
inmanta_plugins/php/model/_init.cf
inmanta_module_php-0.3.7.dist-info/METADATA
inmanta_module_php-0.3.7.dist-info/WHEEL
inmanta_module_php-0.3.7.dist-info/top_level.txt
inmanta_module_php-0.3.7.dist-info/RECORD
