Metadata-Version: 2.1
Name: inmanta-module-php
Version: 0.3.7
License: Apache 2.0
Requires-Dist: inmanta-module-std
Requires-Dist: inmanta-module-web
Requires-Dist: inmanta-module-yum
